README.md
setup.py
microanalytics/__init__.py
microanalytics.egg-info/PKG-INFO
microanalytics.egg-info/SOURCES.txt
microanalytics.egg-info/dependency_links.txt
microanalytics.egg-info/top_level.txt